{
  "data": {
    "id": 1,
    "attributes": {
      "Title": "Privacy Policy",
      "Editor": "hotdealsbazaar.com knows that your privacy is very important, and to keep you informed about our privacy practices we ask that you please read the guidelines described below. Keep in mind that because Indiafreestuff.in  is a growing website and internet technologies are constantly evolving, these guidelines are subject to change and any said changes will be posted on this page. hotdealsbazaar.com is a participant in the Amazon Services LLC Associates Program, an affiliate advertising program and Flipkart affiliate program, we may earn commission on your qualifying purchases from our link such as Amazon or Flipkart.\n\n",
      "Meta_title": "hotdealsbazaar.com knows that your privacy is very important",
      "Meta_description": "hotdealsbazaar.com knows that your privacy is very important",
      "createdAt": "2023-09-20T07:12:34.318Z",
      "updatedAt": "2023-09-20T07:17:54.779Z",
      "publishedAt": "2023-09-20T07:15:11.331Z",
      "Featured_image": {
        "data": null
      }
    }
  },
  "meta": {}
}